effects/__init__.py
effects/contrib/__init__.py
effects/contrib/mypy/__init__.py
effects/contrib/mypy/typeclass_plugin.py
effects/py.typed
effects/typeclass.py
effects-0.0.1.dist-info/LICENSE
effects-0.0.1.dist-info/WHEEL
effects-0.0.1.dist-info/METADATA
effects-0.0.1.dist-info/RECORD
